P3DtoPLE/__init__.py
P3DtoPLE/__main__.py
P3DtoPLE/components.py
P3DtoPLE/dotproduct.py
P3DtoPLE/gui.py
P3DtoPLE/isoconfig.py
P3DtoPLE/polydif.py
P3DtoPLE/visualise.py
P3DtoPLE-0.4.dist-info/COPYING.md
P3DtoPLE-0.4.dist-info/METADATA
P3DtoPLE-0.4.dist-info/WHEEL
P3DtoPLE-0.4.dist-info/top_level.txt
P3DtoPLE-0.4.dist-info/RECORD
